{"numTotalTestSuites":77,"numPassedTestSuites":77,"numFailedTestSuites":0,"numPendingTestSuites":0,"numTotalTests":122,"numPassedTests":122,"numFailedTests":0,"numPendingTests":0,"numTodoTests":0,"snapshot":{"added":0,"failure":false,"filesAdded":0,"filesRemoved":0,"filesRemovedList":[],"filesUnmatched":0,"filesUpdated":0,"matched":0,"total":0,"unchecked":0,"uncheckedKeysByFile":[],"unmatched":0,"updated":0,"didUpdate":false},"startTime":1758243299051,"success":true,"testResults":[{"assertionResults":[{"ancestorTitles":["PositionStore contract: core & services-adapter"],"fullName":"PositionStore contract: core & services-adapter core: CRUD & isolation","status":"passed","title":"core: CRUD & isolation","duration":29.623800000000074,"failureMessages":[],"meta":{}}],"startTime":1758243303593,"endTime":1758243303622.6238,"status":"passed","message":"","name":"C:/Users/Admin/dev/zaif-trade-bot/__tests__/unit/contracts/position-store.contract.test.ts"},{"assertionResults":[{"ancestorTitles":["RiskManager contract"],"fullName":"RiskManager contract core: validateOrder returns error for invalid intent","status":"passed","title":"core: validateOrder returns error for invalid intent","duration":7.203399999999988,"failureMessages":[],"meta":{}},{"ancestorTitles":["RiskManager contract"],"fullName":"RiskManager contract core: clampExposure clamps qty by positionPct","status":"passed","title":"core: clampExposure clamps qty by positionPct","duration":4.92330000000004,"failureMessages":[],"meta":{}},{"ancestorTitles":["RiskManager contract"],"fullName":"RiskManager contract core: manageTrailingStop produces trigger","status":"passed","title":"core: manageTrailingStop produces trigger","duration":2.9589999999999463,"failureMessages":[],"meta":{}}],"startTime":1758243304743,"endTime":1758243304758.959,"status":"passed","message":"","name":"C:/Users/Admin/dev/zaif-trade-bot/__tests__/unit/contracts/risk.contract.test.ts"},{"assertionResults":[{"ancestorTitles":["BaseStrategy"],"fullName":"BaseStrategy calls hooks in order","status":"passed","title":"calls hooks in order","duration":7.282000000000039,"failureMessages":[],"meta":{}}],"startTime":1758243305574,"endTime":1758243305581.282,"status":"passed","message":"","name":"C:/Users/Admin/dev/zaif-trade-bot/__tests__/unit/core/base-strategy.test.ts"},{"assertionResults":[{"ancestorTitles":["core/execution minimal coverage"],"fullName":"core/execution minimal coverage submitOrderWithRetry DRY_RUN returns immediate filled summary","status":"passed","title":"submitOrderWithRetry DRY_RUN returns immediate filled summary","duration":12.630699999999706,"failureMessages":[],"meta":{}},{"ancestorTitles":["core/execution minimal coverage"],"fullName":"core/execution minimal coverage onExitFill updates stats and reduces position qty (success path)","status":"passed","title":"onExitFill updates stats and reduces position qty (success path)","duration":74.88119999999981,"failureMessages":[],"meta":{}},{"ancestorTitles":["core/execution minimal coverage"],"fullName":"core/execution minimal coverage cancelOrder throws on API error (propagates)","status":"passed","title":"cancelOrder throws on API error (propagates)","duration":8.529700000000048,"failureMessages":[],"meta":{}}],"startTime":1758243302341,"endTime":1758243302436.5298,"status":"passed","message":"","name":"C:/Users/Admin/dev/zaif-trade-bot/__tests__/unit/core/execution.core.test.ts"},{"assertionResults":[{"ancestorTitles":["core/risk/guards.validateOrderPlacement"],"fullName":"core/risk/guards.validateOrderPlacement blocks when qty below min trade size","status":"passed","title":"blocks when qty below min trade size","duration":6.859400000000051,"failureMessages":[],"meta":{}},{"ancestorTitles":["core/risk/guards.validateOrderPlacement"],"fullName":"core/risk/guards.validateOrderPlacement blocks when position + buy qty exceeds max position size","status":"passed","title":"blocks when position + buy qty exceeds max position size","duration":2.8999999999998636,"failureMessages":[],"meta":{}},{"ancestorTitles":["core/risk/guards.validateOrderPlacement"],"fullName":"core/risk/guards.validateOrderPlacement blocks SELL when current position already exceeds max position size","status":"passed","title":"blocks SELL when current position already exceeds max position size","duration":2.405899999999974,"failureMessages":[],"meta":{}},{"ancestorTitles":["core/risk/guards.validateOrderPlacement"],"fullName":"core/risk/guards.validateOrderPlacement blocks when notional exceeds max","status":"passed","title":"blocks when notional exceeds max","duration":2.5610999999998967,"failureMessages":[],"meta":{}},{"ancestorTitles":["core/risk/guards.validateOrderPlacement"],"fullName":"core/risk/guards.validateOrderPlacement blocks when open orders exceed limit","status":"passed","title":"blocks when open orders exceed limit","duration":2.233799999999974,"failureMessages":[],"meta":{}},{"ancestorTitles":["core/risk/guards.validateOrderPlacement"],"fullName":"core/risk/guards.validateOrderPlacement blocks within cooldown after last exit","status":"passed","title":"blocks within cooldown after last exit","duration":2.310899999999947,"failureMessages":[],"meta":{}},{"ancestorTitles":["core/risk/guards.validateOrderPlacement"],"fullName":"core/risk/guards.validateOrderPlacement allows when all conditions pass","status":"passed","title":"allows when all conditions pass","duration":2.1475000000000364,"failureMessages":[],"meta":{}}],"startTime":1758243304776,"endTime":1758243304798.1475,"status":"passed","message":"","name":"C:/Users/Admin/dev/zaif-trade-bot/__tests__/unit/core/guards.test.ts"},{"assertionResults":[{"ancestorTitles":["core/market"],"fullName":"core/market calcRealizedPnL matches FIFO and sums correctly","status":"passed","title":"calcRealizedPnL matches FIFO and sums correctly","duration":5.701199999999972,"failureMessages":[],"meta":{}}],"startTime":1758243306630,"endTime":1758243306635.7012,"status":"passed","message":"","name":"C:/Users/Admin/dev/zaif-trade-bot/__tests__/unit/core/market.test.ts"},{"assertionResults":[{"ancestorTitles":["max hold guard (core)"],"fullName":"max hold guard (core) emits TIME_LIMIT when hold exceeds MAX_HOLD_SEC","status":"passed","title":"emits TIME_LIMIT when hold exceeds MAX_HOLD_SEC","duration":6.410599999999931,"failureMessages":[],"meta":{}}],"startTime":1758243306286,"endTime":1758243306292.4106,"status":"passed","message":"","name":"C:/Users/Admin/dev/zaif-trade-bot/__tests__/unit/core/max-hold-guard.test.ts"},{"assertionResults":[{"ancestorTitles":["core/position-store recovery"],"fullName":"core/position-store recovery recovers after file corruption on next update","status":"passed","title":"recovers after file corruption on next update","duration":415.50430000000006,"failureMessages":[],"meta":{}},{"ancestorTitles":["core/position-store recovery"],"fullName":"core/position-store recovery remains consistent across very rapid successive saves","status":"passed","title":"remains consistent across very rapid successive saves","duration":222.7260000000001,"failureMessages":[],"meta":{}},{"ancestorTitles":["core/position-store recovery"],"fullName":"core/position-store recovery continues accumulation after recovery","status":"passed","title":"continues accumulation after recovery","duration":17.624500000000353,"failureMessages":[],"meta":{}}],"startTime":1758243300900,"endTime":1758243301556.6245,"status":"passed","message":"","name":"C:/Users/Admin/dev/zaif-trade-bot/__tests__/unit/core/position-store.recovery.test.ts"},{"assertionResults":[{"ancestorTitles":["core/position-store"],"fullName":"core/position-store adds on bid fills and closes on ask fills","status":"passed","title":"adds on bid fills and closes on ask fills","duration":24.658500000000004,"failureMessages":[],"meta":{}}],"startTime":1758243303467,"endTime":1758243303491.6584,"status":"passed","message":"","name":"C:/Users/Admin/dev/zaif-trade-bot/__tests__/unit/core/position-store.test.ts"},{"assertionResults":[{"ancestorTitles":["core/risk"],"fullName":"core/risk calculateSma returns null when not enough data","status":"passed","title":"calculateSma returns null when not enough data","duration":7.390700000000038,"failureMessages":[],"meta":{}},{"ancestorTitles":["core/risk"],"fullName":"core/risk calculateRsi returns 50 when gains=losses=0","status":"passed","title":"calculateRsi returns 50 when gains=losses=0","duration":2.0317000000000007,"failureMessages":[],"meta":{}},{"ancestorTitles":["core/risk"],"fullName":"core/risk positionSizeFromBalance applies pct and rounds","status":"passed","title":"positionSizeFromBalance applies pct and rounds","duration":1.4583000000000084,"failureMessages":[],"meta":{}},{"ancestorTitles":["core/risk"],"fullName":"core/risk evaluateExitConditions yields RSI_EXIT when over threshold","status":"passed","title":"evaluateExitConditions yields RSI_EXIT when over threshold","duration":1.7626000000000204,"failureMessages":[],"meta":{}},{"ancestorTitles":["core/risk"],"fullName":"core/risk evaluateExitConditions yields empty when no condition","status":"passed","title":"evaluateExitConditions yields empty when no condition","duration":1.0086999999999762,"failureMessages":[],"meta":{}}],"startTime":1758243304848,"endTime":1758243304862.0088,"status":"passed","message":"","name":"C:/Users/Admin/dev/zaif-trade-bot/__tests__/unit/core/risk.test.ts"},{"assertionResults":[{"ancestorTitles":["strategies counters"],"fullName":"strategies counters buy-strategy increments buy entry and may increment RSI/trail counters","status":"passed","title":"buy-strategy increments buy entry and may increment RSI/trail counters","duration":730.1488000000002,"failureMessages":[],"meta":{}},{"ancestorTitles":["strategies counters"],"fullName":"strategies counters sell-strategy increments RSI exit and trail counters and sell entry","status":"passed","title":"sell-strategy increments RSI exit and trail counters and sell entry","duration":100.94499999999971,"failureMessages":[],"meta":{}},{"ancestorTitles":["strategies counters"],"fullName":"strategies counters consecutive triggers accumulate counts (RSI and Trail)","status":"passed","title":"consecutive triggers accumulate counts (RSI and Trail)","duration":635.962,"failureMessages":[],"meta":{}}],"startTime":1758243300692,"endTime":1758243302159.962,"status":"passed","message":"","name":"C:/Users/Admin/dev/zaif-trade-bot/__tests__/unit/core/strategies.test.ts"},{"assertionResults":[{"ancestorTitles":["live-minimal DRY_RUN path"],"fullName":"live-minimal DRY_RUN path decideOrderType infers market when rateInput empty","status":"passed","title":"decideOrderType infers market when rateInput empty","duration":1510.5474000000002,"failureMessages":[],"meta":{}}],"startTime":1758243300681,"endTime":1758243302191.5474,"status":"passed","message":"","name":"C:/Users/Admin/dev/zaif-trade-bot/__tests__/unit/tools/live-minimal.test.ts"},{"assertionResults":[{"ancestorTitles":["metrics-dash --json"],"fullName":"metrics-dash --json emits keys rate/cache/events/tradePhase","status":"passed","title":"emits keys rate/cache/events/tradePhase","duration":13.894699999999943,"failureMessages":[],"meta":{}}],"startTime":1758243305340,"endTime":1758243305353.8948,"status":"passed","message":"","name":"C:/Users/Admin/dev/zaif-trade-bot/__tests__/unit/tools/metrics-dash.json.test.ts"},{"assertionResults":[{"ancestorTitles":["report-summary formatted fields"],"fullName":"report-summary formatted fields includes summaryText and top3Table","status":"passed","title":"includes summaryText and top3Table","duration":99.76880000000006,"failureMessages":[],"meta":{}}],"startTime":1758243302159,"endTime":1758243302258.7688,"status":"passed","message":"","name":"C:/Users/Admin/dev/zaif-trade-bot/__tests__/unit/tools/report-summary.format.test.ts"},{"assertionResults":[{"ancestorTitles":["tools/report-summary"],"fullName":"tools/report-summary generates summary for paper source","status":"passed","title":"generates summary for paper source","duration":260.65449999999987,"failureMessages":[],"meta":{}},{"ancestorTitles":["tools/report-summary"],"fullName":"tools/report-summary handles first-run with no diff file","status":"passed","title":"handles first-run with no diff file","duration":446.12620000000015,"failureMessages":[],"meta":{}}],"startTime":1758243300683,"endTime":1758243301390.1262,"status":"passed","message":"","name":"C:/Users/Admin/dev/zaif-trade-bot/__tests__/unit/tools/report-summary.test.ts"},{"assertionResults":[{"ancestorTitles":["tools/stats-graph"],"fullName":"tools/stats-graph emits svg containing legend and DD text","status":"passed","title":"emits svg containing legend and DD text","duration":114.93799999999999,"failureMessages":[],"meta":{}}],"startTime":1758243302193,"endTime":1758243302307.938,"status":"passed","message":"","name":"C:/Users/Admin/dev/zaif-trade-bot/__tests__/unit/tools/stats-graph.test.ts"},{"assertionResults":[{"ancestorTitles":["trade-config mapping"],"fullName":"trade-config mapping normalizes and maps orders per phase","status":"passed","title":"normalizes and maps orders per phase","duration":5.801400000000058,"failureMessages":[],"meta":{}}],"startTime":1758243306369,"endTime":1758243306374.8015,"status":"passed","message":"","name":"C:/Users/Admin/dev/zaif-trade-bot/__tests__/unit/tools/trade-config.mapping.test.ts"},{"assertionResults":[{"ancestorTitles":["trade-config"],"fullName":"trade-config normalizes and maps phase to ordersPerDay","status":"passed","title":"normalizes and maps phase to ordersPerDay","duration":5.656900000000064,"failureMessages":[],"meta":{}}],"startTime":1758243306523,"endTime":1758243306528.657,"status":"passed","message":"","name":"C:/Users/Admin/dev/zaif-trade-bot/__tests__/unit/tools/trade-config.test.ts"},{"assertionResults":[{"ancestorTitles":["trade-live dry-run"],"fullName":"trade-live dry-run emits plan and returns summary","status":"passed","title":"emits plan and returns summary","duration":10.452600000000075,"failureMessages":[],"meta":{}}],"startTime":1758243305813,"endTime":1758243305823.4526,"status":"passed","message":"","name":"C:/Users/Admin/dev/zaif-trade-bot/__tests__/unit/tools/trade-live.dryrun.test.ts"},{"assertionResults":[{"ancestorTitles":["trade-state promotion"],"fullName":"trade-state promotion promotes 1->2 after consecutive days","status":"passed","title":"promotes 1->2 after consecutive days","duration":6.8827,"failureMessages":[],"meta":{}},{"ancestorTitles":["trade-state promotion"],"fullName":"trade-state promotion promotes 2->3 and 3->4 by total success","status":"passed","title":"promotes 2->3 and 3->4 by total success","duration":2.404700000000048,"failureMessages":[],"meta":{}}],"startTime":1758243305814,"endTime":1758243305823.4048,"status":"passed","message":"","name":"C:/Users/Admin/dev/zaif-trade-bot/__tests__/unit/tools/trade-state.test.ts"},{"assertionResults":[{"ancestorTitles":["daily-stats edge/error"],"fullName":"daily-stats edge/error loadDaily returns defaults when file missing","status":"passed","title":"loadDaily returns defaults when file missing","duration":18.7188000000001,"failureMessages":[],"meta":{}},{"ancestorTitles":["daily-stats edge/error"],"fullName":"daily-stats edge/error loadDaily returns defaults on corrupted JSON","status":"passed","title":"loadDaily returns defaults on corrupted JSON","duration":7.899199999999837,"failureMessages":[],"meta":{}},{"ancestorTitles":["daily-stats edge/error"],"fullName":"daily-stats edge/error appendFillPnl swallows write errors gracefully","status":"passed","title":"appendFillPnl swallows write errors gracefully","duration":18.49700000000007,"failureMessages":[],"meta":{}}],"startTime":1758243303801,"endTime":1758243303846.497,"status":"passed","message":"","name":"C:/Users/Admin/dev/zaif-trade-bot/__tests__/unit/utils/daily-stats.edge.test.ts"},{"assertionResults":[{"ancestorTitles":["daily-stats metrics"],"fullName":"daily-stats metrics maxDrawdown and maxConsecLosses update with mixed pnl","status":"passed","title":"maxDrawdown and maxConsecLosses update with mixed pnl","duration":18.64390000000003,"failureMessages":[],"meta":{}},{"ancestorTitles":["daily-stats metrics"],"fullName":"daily-stats metrics avgHoldSec accumulates from durationMs","status":"passed","title":"avgHoldSec accumulates from durationMs","duration":29.771400000000085,"failureMessages":[],"meta":{}}],"startTime":1758243303461,"endTime":1758243303508.7715,"status":"passed","message":"","name":"C:/Users/Admin/dev/zaif-trade-bot/__tests__/unit/utils/daily-stats.metrics.test.ts"},{"assertionResults":[{"ancestorTitles":["daily-stats"],"fullName":"daily-stats incBuyEntry and appendFillPnl update JSON","status":"passed","title":"incBuyEntry and appendFillPnl update JSON","duration":19.805900000000065,"failureMessages":[],"meta":{}},{"ancestorTitles":["daily-stats"],"fullName":"daily-stats incSellEntry twice and negative pnl accumulates","status":"passed","title":"incSellEntry twice and negative pnl accumulates","duration":18.699700000000007,"failureMessages":[],"meta":{}}],"startTime":1758243303282,"endTime":1758243303321.6997,"status":"passed","message":"","name":"C:/Users/Admin/dev/zaif-trade-bot/__tests__/unit/utils/daily-stats.test.ts"},{"assertionResults":[{"ancestorTitles":["daily-stats TTL eviction"],"fullName":"daily-stats TTL eviction evicts stale cache entries and reloads from disk","status":"passed","title":"evicts stale cache entries and reloads from disk","duration":29.11779999999999,"failureMessages":[],"meta":{}}],"startTime":1758243304347,"endTime":1758243304376.118,"status":"passed","message":"","name":"C:/Users/Admin/dev/zaif-trade-bot/__tests__/unit/utils/daily-stats.ttl.test.ts"},{"assertionResults":[{"ancestorTitles":["features-logger interval flush"],"fullName":"features-logger interval flush flushes by interval when enabled","status":"passed","title":"flushes by interval when enabled","duration":276.9213,"failureMessages":[],"meta":{}}],"startTime":1758243300681,"endTime":1758243300957.9214,"status":"passed","message":"","name":"C:/Users/Admin/dev/zaif-trade-bot/__tests__/unit/utils/features-logger.interval.test.ts"},{"assertionResults":[{"ancestorTitles":["features-logger"],"fullName":"features-logger writes JSONL line and JSON latest","status":"passed","title":"writes JSONL line and JSON latest","duration":43.99950000000001,"failureMessages":[],"meta":{}}],"startTime":1758243302174,"endTime":1758243302217.9995,"status":"passed","message":"","name":"C:/Users/Admin/dev/zaif-trade-bot/__tests__/unit/utils/features-logger.test.ts"},{"assertionResults":[{"ancestorTitles":["utils: new indicator series sanity"],"fullName":"utils: new indicator series sanity heikin ashi produces smoothed values","status":"passed","title":"heikin ashi produces smoothed values","duration":7.130400000000009,"failureMessages":[],"meta":{}},{"ancestorTitles":["utils: new indicator series sanity"],"fullName":"utils: new indicator series sanity vortex in [0, +inf) with null padding","status":"passed","title":"vortex in [0, +inf) with null padding","duration":3.97420000000011,"failureMessages":[],"meta":{}},{"ancestorTitles":["utils: new indicator series sanity"],"fullName":"utils: new indicator series sanity aroon in [0,100] and oscillator in [-100,100]","status":"passed","title":"aroon in [0,100] and oscillator in [-100,100]","duration":3.6222999999999956,"failureMessages":[],"meta":{}},{"ancestorTitles":["utils: new indicator series sanity"],"fullName":"utils: new indicator series sanity tsi and signal exist and reasonable sign","status":"passed","title":"tsi and signal exist and reasonable sign","duration":2.762899999999945,"failureMessages":[],"meta":{}},{"ancestorTitles":["utils: new indicator series sanity"],"fullName":"utils: new indicator series sanity mfi in [0,100]","status":"passed","title":"mfi in [0,100]","duration":5.127300000000105,"failureMessages":[],"meta":{}},{"ancestorTitles":["utils: new indicator series sanity"],"fullName":"utils: new indicator series sanity obv accumulates directionally","status":"passed","title":"obv accumulates directionally","duration":5.855000000000018,"failureMessages":[],"meta":{}},{"ancestorTitles":["utils: new indicator series sanity"],"fullName":"utils: new indicator series sanity keltner bands have upper>=basis>=lower","status":"passed","title":"keltner bands have upper>=basis>=lower","duration":3.2841000000000804,"failureMessages":[],"meta":{}},{"ancestorTitles":["utils: new indicator series sanity"],"fullName":"utils: new indicator series sanity donchian upper>=mid>=lower","status":"passed","title":"donchian upper>=mid>=lower","duration":4.405299999999897,"failureMessages":[],"meta":{}},{"ancestorTitles":["utils: new indicator series sanity"],"fullName":"utils: new indicator series sanity choppiness in [0,100]","status":"passed","title":"choppiness in [0,100]","duration":5.6486999999999625,"failureMessages":[],"meta":{}}],"startTime":1758243303459,"endTime":1758243303500.6487,"status":"passed","message":"","name":"C:/Users/Admin/dev/zaif-trade-bot/__tests__/unit/utils/indicators.new-series.test.ts"},{"assertionResults":[{"ancestorTitles":["utils/indicators","Moving Averages"],"fullName":"utils/indicators Moving Averages sma calculates simple moving average","status":"passed","title":"sma calculates simple moving average","duration":7.191100000000006,"failureMessages":[],"meta":{}},{"ancestorTitles":["utils/indicators","Moving Averages"],"fullName":"utils/indicators Moving Averages ema calculates exponential moving average","status":"passed","title":"ema calculates exponential moving average","duration":2.9873000000000047,"failureMessages":[],"meta":{}},{"ancestorTitles":["utils/indicators","Moving Averages"],"fullName":"utils/indicators Moving Averages wma calculates weighted moving average","status":"passed","title":"wma calculates weighted moving average","duration":2.6371999999998934,"failureMessages":[],"meta":{}},{"ancestorTitles":["utils/indicators","Moving Averages"],"fullName":"utils/indicators Moving Averages hma calculates Hull moving average","status":"passed","title":"hma calculates Hull moving average","duration":2.468499999999949,"failureMessages":[],"meta":{}},{"ancestorTitles":["utils/indicators","Moving Averages"],"fullName":"utils/indicators Moving Averages kama calculates Kaufman's Adaptive Moving Average","status":"passed","title":"kama calculates Kaufman's Adaptive Moving Average","duration":2.9465000000000146,"failureMessages":[],"meta":{}},{"ancestorTitles":["utils/indicators","Oscillators & Momentum"],"fullName":"utils/indicators Oscillators & Momentum rsi calculates Relative Strength Index","status":"passed","title":"rsi calculates Relative Strength Index","duration":4.5103999999998905,"failureMessages":[],"meta":{}},{"ancestorTitles":["utils/indicators","Oscillators & Momentum"],"fullName":"utils/indicators Oscillators & Momentum macd calculates Moving Average Convergence Divergence","status":"passed","title":"macd calculates Moving Average Convergence Divergence","duration":3.1782000000000608,"failureMessages":[],"meta":{}},{"ancestorTitles":["utils/indicators","Oscillators & Momentum"],"fullName":"utils/indicators Oscillators & Momentum stochastic calculates Stochastic Oscillator","status":"passed","title":"stochastic calculates Stochastic Oscillator","duration":2.9613999999999123,"failureMessages":[],"meta":{}},{"ancestorTitles":["utils/indicators","Oscillators & Momentum"],"fullName":"utils/indicators Oscillators & Momentum williamsR calculates Williams %R","status":"passed","title":"williamsR calculates Williams %R","duration":2.238299999999981,"failureMessages":[],"meta":{}},{"ancestorTitles":["utils/indicators","Oscillators & Momentum"],"fullName":"utils/indicators Oscillators & Momentum cci calculates Commodity Channel Index","status":"passed","title":"cci calculates Commodity Channel Index","duration":3.6026999999999134,"failureMessages":[],"meta":{}},{"ancestorTitles":["utils/indicators","Oscillators & Momentum"],"fullName":"utils/indicators Oscillators & Momentum roc calculates Rate of Change","status":"passed","title":"roc calculates Rate of Change","duration":3.6929000000000087,"failureMessages":[],"meta":{}},{"ancestorTitles":["utils/indicators","Oscillators & Momentum"],"fullName":"utils/indicators Oscillators & Momentum momentum calculates momentum","status":"passed","title":"momentum calculates momentum","duration":2.0213000000001102,"failureMessages":[],"meta":{}},{"ancestorTitles":["utils/indicators","Oscillators & Momentum"],"fullName":"utils/indicators Oscillators & Momentum deviationPct calculates price deviation percentage","status":"passed","title":"deviationPct calculates price deviation percentage","duration":2.088999999999942,"failureMessages":[],"meta":{}},{"ancestorTitles":["utils/indicators","Volatility & Bands"],"fullName":"utils/indicators Volatility & Bands stddev calculates standard deviation","status":"passed","title":"stddev calculates standard deviation","duration":2.1416999999999007,"failureMessages":[],"meta":{}},{"ancestorTitles":["utils/indicators","Volatility & Bands"],"fullName":"utils/indicators Volatility & Bands bollinger calculates Bollinger Bands","status":"passed","title":"bollinger calculates Bollinger Bands","duration":2.2796999999998206,"failureMessages":[],"meta":{}},{"ancestorTitles":["utils/indicators","Volatility & Bands"],"fullName":"utils/indicators Volatility & Bands bbWidth calculates Bollinger Band Width","status":"passed","title":"bbWidth calculates Bollinger Band Width","duration":3.401200000000017,"failureMessages":[],"meta":{}},{"ancestorTitles":["utils/indicators","Volatility & Bands"],"fullName":"utils/indicators Volatility & Bands bollinger returns nulls when not enough data","status":"passed","title":"bollinger returns nulls when not enough data","duration":2.392900000000054,"failureMessages":[],"meta":{}},{"ancestorTitles":["utils/indicators","Volatility & Bands"],"fullName":"utils/indicators Volatility & Bands envelopes calculates moving average envelopes","status":"passed","title":"envelopes calculates moving average envelopes","duration":2.321899999999914,"failureMessages":[],"meta":{}},{"ancestorTitles":["utils/indicators","Volatility & Bands"],"fullName":"utils/indicators Volatility & Bands atr calculates Average True Range","status":"passed","title":"atr calculates Average True Range","duration":2.299400000000105,"failureMessages":[],"meta":{}},{"ancestorTitles":["utils/indicators","Volatility & Bands"],"fullName":"utils/indicators Volatility & Bands donchianWidth calculates Donchian Channel width","status":"passed","title":"donchianWidth calculates Donchian Channel width","duration":1.7910000000001673,"failureMessages":[],"meta":{}},{"ancestorTitles":["utils/indicators","Volatility & Bands"],"fullName":"utils/indicators Volatility & Bands donchianWidth returns null when close is zero","status":"passed","title":"donchianWidth returns null when close is zero","duration":1.6772000000000844,"failureMessages":[],"meta":{}},{"ancestorTitles":["utils/indicators","Other Indicators"],"fullName":"utils/indicators Other Indicators ichimoku calculates Ichimoku Cloud values","status":"passed","title":"ichimoku calculates Ichimoku Cloud values","duration":1.8847999999998137,"failureMessages":[],"meta":{}},{"ancestorTitles":["utils/indicators","Other Indicators"],"fullName":"utils/indicators Other Indicators dmiAdx calculates DMI and ADX","status":"passed","title":"dmiAdx calculates DMI and ADX","duration":2.5441000000000713,"failureMessages":[],"meta":{}},{"ancestorTitles":["utils/indicators","Other Indicators"],"fullName":"utils/indicators Other Indicators dmiAdx handles no-move series as zeros","status":"passed","title":"dmiAdx handles no-move series as zeros","duration":5.0586000000000695,"failureMessages":[],"meta":{}},{"ancestorTitles":["utils/indicators","Other Indicators"],"fullName":"utils/indicators Other Indicators psarStep calculates one step of Parabolic SAR","status":"passed","title":"psarStep calculates one step of Parabolic SAR","duration":2.162399999999934,"failureMessages":[],"meta":{}},{"ancestorTitles":["utils/indicators","Other Indicators"],"fullName":"utils/indicators Other Indicators fibPosition calculates Fibonacci position","status":"passed","title":"fibPosition calculates Fibonacci position","duration":1.9423000000001593,"failureMessages":[],"meta":{}},{"ancestorTitles":["utils/indicators","Edge Cases & Guards"],"fullName":"utils/indicators Edge Cases & Guards stochastic returns nulls when insufficient length","status":"passed","title":"stochastic returns nulls when insufficient length","duration":2.2910000000001673,"failureMessages":[],"meta":{}},{"ancestorTitles":["utils/indicators","Edge Cases & Guards"],"fullName":"utils/indicators Edge Cases & Guards ichimoku returns nulls when insufficient window","status":"passed","title":"ichimoku returns nulls when insufficient window","duration":1.9961000000000695,"failureMessages":[],"meta":{}},{"ancestorTitles":["utils/indicators","Edge Cases & Guards"],"fullName":"utils/indicators Edge Cases & Guards macd returns nulls before slow+signal seed","status":"passed","title":"macd returns nulls before slow+signal seed","duration":2.0398999999999887,"failureMessages":[],"meta":{}},{"ancestorTitles":["utils/indicators","Edge Cases & Guards"],"fullName":"utils/indicators Edge Cases & Guards roc returns null if previous value is zero","status":"passed","title":"roc returns null if previous value is zero","duration":6.726799999999912,"failureMessages":[],"meta":{}}],"startTime":1758243300700,"endTime":1758243300789.7268,"status":"passed","message":"","name":"C:/Users/Admin/dev/zaif-trade-bot/__tests__/unit/utils/indicators.test.ts"},{"assertionResults":[{"ancestorTitles":["trend indicators"],"fullName":"trend indicators computes MACD(12,26,9)","status":"passed","title":"computes MACD(12,26,9)","duration":8.903799999999933,"failureMessages":[],"meta":{}},{"ancestorTitles":["trend indicators"],"fullName":"trend indicators computes ADX(14)","status":"passed","title":"computes ADX(14)","duration":3.219699999999989,"failureMessages":[],"meta":{}},{"ancestorTitles":["trend indicators"],"fullName":"trend indicators computes Bollinger(20,2)","status":"passed","title":"computes Bollinger(20,2)","duration":3.4149999999999636,"failureMessages":[],"meta":{}},{"ancestorTitles":["trend indicators"],"fullName":"trend indicators computes Ichimoku(9,26,52)","status":"passed","title":"computes Ichimoku(9,26,52)","duration":2.5412999999999784,"failureMessages":[],"meta":{}},{"ancestorTitles":["trend indicators"],"fullName":"trend indicators computes ATR(10) and SuperTrend(10,3)","status":"passed","title":"computes ATR(10) and SuperTrend(10,3)","duration":7.1544999999999845,"failureMessages":[],"meta":{}}],"startTime":1758243304580,"endTime":1758243304606.1545,"status":"passed","message":"","name":"C:/Users/Admin/dev/zaif-trade-bot/__tests__/unit/utils/indicators.trend.test.ts"},{"assertionResults":[{"ancestorTitles":["logger JSON required meta and redaction"],"fullName":"logger JSON required meta and redaction emits JSON with redacted fields","status":"passed","title":"emits JSON with redacted fields","duration":11.278800000000047,"failureMessages":[],"meta":{}}],"startTime":1758243305574,"endTime":1758243305585.2788,"status":"passed","message":"","name":"C:/Users/Admin/dev/zaif-trade-bot/__tests__/unit/utils/logger.meta.snapshot.test.ts"},{"assertionResults":[{"ancestorTitles":["utils/logger"],"fullName":"utils/logger respects LOG_LEVEL='TRACE' threshold","status":"passed","title":"respects LOG_LEVEL='TRACE' threshold","duration":8.882600000000025,"failureMessages":[],"meta":{}},{"ancestorTitles":["utils/logger"],"fullName":"utils/logger respects LOG_LEVEL='DEBUG' threshold","status":"passed","title":"respects LOG_LEVEL='DEBUG' threshold","duration":2.234299999999962,"failureMessages":[],"meta":{}},{"ancestorTitles":["utils/logger"],"fullName":"utils/logger respects LOG_LEVEL='INFO' threshold","status":"passed","title":"respects LOG_LEVEL='INFO' threshold","duration":1.0144000000000233,"failureMessages":[],"meta":{}},{"ancestorTitles":["utils/logger"],"fullName":"utils/logger respects LOG_LEVEL='WARN' threshold","status":"passed","title":"respects LOG_LEVEL='WARN' threshold","duration":1.1562999999999874,"failureMessages":[],"meta":{}},{"ancestorTitles":["utils/logger"],"fullName":"utils/logger respects LOG_LEVEL='ERROR' threshold","status":"passed","title":"respects LOG_LEVEL='ERROR' threshold","duration":0.8659000000000106,"failureMessages":[],"meta":{}},{"ancestorTitles":["utils/logger"],"fullName":"utils/logger respects LOG_LEVEL='FATAL' threshold","status":"passed","title":"respects LOG_LEVEL='FATAL' threshold","duration":0.8718000000000075,"failureMessages":[],"meta":{}},{"ancestorTitles":["utils/logger"],"fullName":"utils/logger outputs JSON when LOG_JSON=1 and includes meta","status":"passed","title":"outputs JSON when LOG_JSON=1 and includes meta","duration":2.713700000000017,"failureMessages":[],"meta":{}},{"ancestorTitles":["utils/logger"],"fullName":"utils/logger suppresses non-error logs in TEST_MODE","status":"passed","title":"suppresses non-error logs in TEST_MODE","duration":0.8839000000000397,"failureMessages":[],"meta":{}}],"startTime":1758243304709,"endTime":1758243304727.8838,"status":"passed","message":"","name":"C:/Users/Admin/dev/zaif-trade-bot/__tests__/unit/utils/logger.test.ts"},{"assertionResults":[{"ancestorTitles":["utils/price-cache"],"fullName":"utils/price-cache loadPriceCache returns [] when file missing","status":"passed","title":"loadPriceCache returns [] when file missing","duration":8.861699999999928,"failureMessages":[],"meta":{}},{"ancestorTitles":["utils/price-cache"],"fullName":"utils/price-cache appendPriceSamples writes and getPriceSeries returns latest first","status":"passed","title":"appendPriceSamples writes and getPriceSeries returns latest first","duration":25.604600000000005,"failureMessages":[],"meta":{}},{"ancestorTitles":["utils/price-cache"],"fullName":"utils/price-cache enforces MAX_ENTRIES by trimming oldest","status":"passed","title":"enforces MAX_ENTRIES by trimming oldest","duration":32.94870000000003,"failureMessages":[],"meta":{}}],"startTime":1758243303172,"endTime":1758243303239.9487,"status":"passed","message":"","name":"C:/Users/Admin/dev/zaif-trade-bot/__tests__/unit/utils/price-cache.test.ts"},{"assertionResults":[{"ancestorTitles":["utils/result"],"fullName":"utils/result ok returns expected shape","status":"passed","title":"ok returns expected shape","duration":5.6679000000000315,"failureMessages":[],"meta":{}},{"ancestorTitles":["utils/result"],"fullName":"utils/result err returns expected shape","status":"passed","title":"err returns expected shape","duration":7.918099999999981,"failureMessages":[],"meta":{}}],"startTime":1758243305574,"endTime":1758243305587.9182,"status":"passed","message":"","name":"C:/Users/Admin/dev/zaif-trade-bot/__tests__/unit/utils/result.test.ts"},{"assertionResults":[{"ancestorTitles":["utils/signer"],"fullName":"utils/signer signBody returns deterministic HMAC","status":"passed","title":"signBody returns deterministic HMAC","duration":7.110200000000077,"failureMessages":[],"meta":{}},{"ancestorTitles":["utils/signer"],"fullName":"utils/signer createNonce is monotonic and respects base","status":"passed","title":"createNonce is monotonic and respects base","duration":4.4862000000000535,"failureMessages":[],"meta":{}},{"ancestorTitles":["utils/signer"],"fullName":"utils/signer createFlexibleNonce strictly increases within same ms","status":"passed","title":"createFlexibleNonce strictly increases within same ms","duration":2.5655000000000427,"failureMessages":[],"meta":{}}],"startTime":1758243305341,"endTime":1758243305355.5654,"status":"passed","message":"","name":"C:/Users/Admin/dev/zaif-trade-bot/__tests__/unit/utils/signer.test.ts"},{"assertionResults":[{"ancestorTitles":["utils: daily-stats summarizeDaily and features-logger error handling"],"fullName":"utils: daily-stats summarizeDaily and features-logger error handling summarizeDaily handles zero trades gracefully","status":"passed","title":"summarizeDaily handles zero trades gracefully","duration":14.48849999999993,"failureMessages":[],"meta":{}},{"ancestorTitles":["utils: daily-stats summarizeDaily and features-logger error handling"],"fullName":"utils: daily-stats summarizeDaily and features-logger error handling summarizeDaily computes averages without division issues","status":"passed","title":"summarizeDaily computes averages without division issues","duration":34.371000000000095,"failureMessages":[],"meta":{}},{"ancestorTitles":["utils: daily-stats summarizeDaily and features-logger error handling"],"fullName":"utils: daily-stats summarizeDaily and features-logger error handling features-logger swallows IO errors","status":"passed","title":"features-logger swallows IO errors","duration":34.58560000000011,"failureMessages":[],"meta":{}}],"startTime":1758243302159,"endTime":1758243302242.5857,"status":"passed","message":"","name":"C:/Users/Admin/dev/zaif-trade-bot/__tests__/unit/utils/stats-and-features.edge.test.ts"},{"assertionResults":[{"ancestorTitles":["utils/toolkit"],"fullName":"utils/toolkit clampAmountForSafety clamps with SAFETY_MODE=1","status":"passed","title":"clampAmountForSafety clamps with SAFETY_MODE=1","duration":8.477599999999939,"failureMessages":[],"meta":{}},{"ancestorTitles":["utils/toolkit"],"fullName":"utils/toolkit exposure ratio and warn pct","status":"passed","title":"exposure ratio and warn pct","duration":1.3240000000000691,"failureMessages":[],"meta":{}},{"ancestorTitles":["utils/toolkit"],"fullName":"utils/toolkit clampByExposureCap clamps when ratio exceeded","status":"passed","title":"clampByExposureCap clamps when ratio exceeded","duration":1.1714999999999236,"failureMessages":[],"meta":{}},{"ancestorTitles":["utils/toolkit"],"fullName":"utils/toolkit getExposureHardCap and getMaxHoldSec parse env","status":"passed","title":"getExposureHardCap and getMaxHoldSec parse env","duration":0.9170999999998912,"failureMessages":[],"meta":{}},{"ancestorTitles":["utils/toolkit"],"fullName":"utils/toolkit readFeatureCsvRows parses JSONL files only","status":"passed","title":"readFeatureCsvRows parses JSONL files only","duration":6.152599999999893,"failureMessages":[],"meta":{}},{"ancestorTitles":["utils/toolkit"],"fullName":"utils/toolkit readFeatureCsvRows ignores empty/invalid lines and handles missing files","status":"passed","title":"readFeatureCsvRows ignores empty/invalid lines and handles missing files","duration":13.784000000000106,"failureMessages":[],"meta":{}},{"ancestorTitles":["utils/toolkit"],"fullName":"utils/toolkit computeExposureRatio returns 0 when denominator is not positive","status":"passed","title":"computeExposureRatio returns 0 when denominator is not positive","duration":0.8939000000000306,"failureMessages":[],"meta":{}},{"ancestorTitles":["utils/toolkit"],"fullName":"utils/toolkit getFeaturesRoot falls back to logs/features when env unset","status":"passed","title":"getFeaturesRoot falls back to logs/features when env unset","duration":0.9291000000000622,"failureMessages":[],"meta":{}}],"startTime":1758243304711,"endTime":1758243304744.9292,"status":"passed","message":"","name":"C:/Users/Admin/dev/zaif-trade-bot/__tests__/unit/utils/toolkit.test.ts"}]}